[
  { "code": "M00.0", "bezeichnung": "Staphylokokken-Arthritis und Polyarthritis" },
  { "code": "M05.0", "bezeichnung": "Felty-Syndrom" },
  { "code": "M05.3", "bezeichnung": "Rheumatoide Arthritis mit Beteiligung anderer Organe" },
  { "code": "M06.0", "bezeichnung": "Seronegative rheumatoide Arthritis" },
  { "code": "M06.9", "bezeichnung": "Rheumatoide Arthritis, nicht näher bezeichnet" },
  { "code": "M07.3", "bezeichnung": "Sonstige psoriatische Arthropathien" },
  { "code": "M08.0", "bezeichnung": "Juvenile rheumatoide Arthritis" },
  { "code": "M10.0", "bezeichnung": "Idiopathische Gicht" },
  { "code": "M10.9", "bezeichnung": "Gicht, nicht näher bezeichnet" },
  { "code": "M11.2", "bezeichnung": "Andere Chondrokalzinose" },
  { "code": "M12.5", "bezeichnung": "Traumatische Arthropathie" },
  { "code": "M13.9", "bezeichnung": "Arthritis, nicht näher bezeichnet" },
  { "code": "M15.0", "bezeichnung": "Primäre Polyarthrose" },
  { "code": "M15.9", "bezeichnung": "Polyarthrose, nicht näher bezeichnet" },
  { "code": "M16.0", "bezeichnung": "Primäre Koxarthrose, beidseitig" },
  { "code": "M16.1", "bezeichnung": "Sonstige primäre Koxarthrose" },
  { "code": "M16.2", "bezeichnung": "Koxarthrose infolge Dysplasie, beidseitig" },
  { "code": "M16.5", "bezeichnung": "Sonstige sekundäre Koxarthrose, beidseitig" },
  { "code": "M16.9", "bezeichnung": "Koxarthrose, nicht näher bezeichnet" },
  { "code": "M17.0", "bezeichnung": "Primäre Gonarthrose, beidseitig" },
  { "code": "M17.1", "bezeichnung": "Sonstige primäre Gonarthrose" },
  { "code": "M17.3", "bezeichnung": "Sonstige posttraumatische Gonarthrose" },
  { "code": "M17.9", "bezeichnung": "Gonarthrose, nicht näher bezeichnet" },
  { "code": "M18.0", "bezeichnung": "Primäre Rhizarthrose, beidseitig" },
  { "code": "M18.1", "bezeichnung": "Sonstige primäre Rhizarthrose" },
  { "code": "M19.07", "bezeichnung": "Primäre Arthrose: Sprunggelenk und Fuß" },
  { "code": "M19.9", "bezeichnung": "Arthrose, nicht näher bezeichnet" },
  { "code": "M20.0", "bezeichnung": "Fingerdeformitäten (erworben)" },
  { "code": "M20.1", "bezeichnung": "Hallux valgus (erworben)" },
  { "code": "M20.2", "bezeichnung": "Hallux rigidus" },
  { "code": "M20.3", "bezeichnung": "Sonstige Hallux-Deformitäten (erworben)" },
  { "code": "M20.4", "bezeichnung": "Hammerzehe (erworben)" },
  { "code": "M21.0", "bezeichnung": "Valgusdeformität, anderenorts nicht klassifiziert" },
  { "code": "M21.1", "bezeichnung": "Varusdeformität, anderenorts nicht klassifiziert" },
  { "code": "M21.6", "bezeichnung": "Erworbene sonstige Deformitäten des Fußes" },
  { "code": "M22.2", "bezeichnung": "Pathologische Veränderungen im Femoropatellargelenk" },
  { "code": "M22.3", "bezeichnung": "Sonstige Patellaerkrankungen" },
  { "code": "M23.2", "bezeichnung": "Alte Verletzung des Meniskus infolge eines Risses" },
  { "code": "M23.3", "bezeichnung": "Sonstige Meniskusveränderungen" },
  { "code": "M23.4", "bezeichnung": "Freier Gelenkkörper im Kniegelenk" },
  { "code": "M23.5", "bezeichnung": "Chronische Instabilität des Kniegelenkes" },
  { "code": "M23.60", "bezeichnung": "Binnenschädigungen Kniegelenk: Vorderes Kreuzband" },
  { "code": "M23.61", "bezeichnung": "Binnenschädigungen Kniegelenk: Hinteres Kreuzband" },
  { "code": "M23.62", "bezeichnung": "Binnenschädigungen Kniegelenk: Mediales Seitenband" },
  { "code": "M23.63", "bezeichnung": "Binnenschädigungen Kniegelenk: Laterales Seitenband" },
  { "code": "M24.1", "bezeichnung": "Sonstige Gelenkveränderungen, anderenorts nicht klassifiziert" },
  { "code": "M24.2", "bezeichnung": "Gelenksteife" },
  { "code": "M24.4", "bezeichnung": "Wiederkehrende Gelenkluxation" },
  { "code": "M24.5", "bezeichnung": "Gelenkkontraktur" },
  { "code": "M25.0", "bezeichnung": "Gelenkerguss" },
  { "code": "M25.1", "bezeichnung": "Fistelbildung am Gelenk" },
  { "code": "M25.3", "bezeichnung": "Sonstige Gelenkinstabilität" },
  { "code": "M25.5", "bezeichnung": "Gelenkschmerz" },
  { "code": "M25.6", "bezeichnung": "Gelenksteife" },
  { "code": "M40.0", "bezeichnung": "Haltungsrundrücken (Kyphose)" },
  { "code": "M40.1", "bezeichnung": "Sonstige sekundäre Kyphose" },
  { "code": "M40.2", "bezeichnung": "Sonstige und nicht näher bezeichnete Kyphose" },
  { "code": "M40.3", "bezeichnung": "Flachrücken" },
  { "code": "M40.4", "bezeichnung": "Sonstige Lordose" },
  { "code": "M40.5", "bezeichnung": "Lordose, nicht näher bezeichnet" },
  { "code": "M41.0", "bezeichnung": "Infantile idiopathische Skoliose" },
  { "code": "M41.1", "bezeichnung": "Juvenile idiopathische Skoliose" },
  { "code": "M41.2", "bezeichnung": "Sonstige idiopathische Skoliosen" },
  { "code": "M41.9", "bezeichnung": "Skoliose, nicht näher bezeichnet" },
  { "code": "M42.0", "bezeichnung": "Juvenile Osteochondrose der Wirbelsäule" },
  { "code": "M43.0", "bezeichnung": "Spondylolyse" },
  { "code": "M43.1", "bezeichnung": "Spondylolisthese" },
  { "code": "M43.6", "bezeichnung": "Torticollis" },
  { "code": "M45", "bezeichnung": "Spondylitis ankylosans" },
  { "code": "M47.0", "bezeichnung": "Arterienkompression bei Spondylose" },
  { "code": "M47.8", "bezeichnung": "Sonstige Spondylose" },
  { "code": "M47.9", "bezeichnung": "Spondylose, nicht näher bezeichnet" },
  { "code": "M48.0", "bezeichnung": "Spinale Stenose" },
  { "code": "M48.1", "bezeichnung": "Kissing spine" },
  { "code": "M50.0", "bezeichnung": "Zervikaler Bandscheibenvorfall mit Myelopathie" },
  { "code": "M50.1", "bezeichnung": "Zervikaler Bandscheibenvorfall mit Radikulopathie" },
  { "code": "M50.2", "bezeichnung": "Sonstige Bandscheibenverlagerung im Halsbereich" },
  { "code": "M50.3", "bezeichnung": "Sonstige Bandscheibendegeneration im Halsbereich" },
  { "code": "M51.0", "bezeichnung": "Lumbaler Bandscheibenvorfall mit Myelopathie" },
  { "code": "M51.1", "bezeichnung": "Lumbaler Bandscheibenvorfall mit Radikulopathie" },
  { "code": "M51.2", "bezeichnung": "Sonstige Bandscheibenverlagerung" },
  { "code": "M51.3", "bezeichnung": "Sonstige Bandscheibendegeneration" },
  { "code": "M51.4", "bezeichnung": "Schmorl-Knötchen" },
  { "code": "M53.1", "bezeichnung": "Zervikobrachial-Syndrom" },
  { "code": "M53.2", "bezeichnung": "Instabilität der Wirbelsäule" },
  { "code": "M53.3", "bezeichnung": "Sacrococcygeale Störungen, anderenorts nicht klassifiziert" },
  { "code": "M54.0", "bezeichnung": "Pannikulitis" },
  { "code": "M54.1", "bezeichnung": "Radikulopathie" },
  { "code": "M54.2", "bezeichnung": "Zervikalgie" },
  { "code": "M54.3", "bezeichnung": "Ischialgie" },
  { "code": "M54.4", "bezeichnung": "Lumboischialgie" },
  { "code": "M54.5", "bezeichnung": "Kreuzschmerz (Lumbago)" },
  { "code": "M54.6", "bezeichnung": "Schmerzen im Bereich der Brustwirbelsäule" },
  { "code": "M54.9", "bezeichnung": "Rückenschmerzen, nicht näher bezeichnet" },
  { "code": "M60.0", "bezeichnung": "Infektiöse Myositis" },
  { "code": "M60.9", "bezeichnung": "Myositis, nicht näher bezeichnet" },
  { "code": "M61.0", "bezeichnung": "Myositis ossificans traumatica" },
  { "code": "M62.0", "bezeichnung": "Muskeldiastase" },
  { "code": "M62.1", "bezeichnung": "Sonstige Muskelruptur" },
  { "code": "M62.3", "bezeichnung": "Immobilisationssyndrom" },
  { "code": "M62.4", "bezeichnung": "Muskelkontraktur" },
  { "code": "M62.5", "bezeichnung": "Muskelschwund und -atrophie, anderenorts nicht klassifiziert" },
  { "code": "M62.6", "bezeichnung": "Muskelzerrung" },
  { "code": "M65.0", "bezeichnung": "Sehnenscheidenabszess" },
  { "code": "M65.3", "bezeichnung": "Schnellender Finger" },
  { "code": "M65.9", "bezeichnung": "Synovitis und Tenosynovitis, nicht näher bezeichnet" },
  { "code": "M66.0", "bezeichnung": "Poplitealzyste" },
  { "code": "M66.2", "bezeichnung": "Spontanruptur von Strecksehnen" },
  { "code": "M66.3", "bezeichnung": "Spontanruptur von Beugesehnen" },
  { "code": "M70.0", "bezeichnung": "Chronische Krepitation des Handgelenkes und der Hand" },
  { "code": "M70.2", "bezeichnung": "Bursitis praepatellaris" },
  { "code": "M70.3", "bezeichnung": "Sonstige Bursitis am Knie" },
  { "code": "M70.5", "bezeichnung": "Sonstige Bursitis am Ellenbogen" },
  { "code": "M70.6", "bezeichnung": "Bursitis trochanterica" },
  { "code": "M70.7", "bezeichnung": "Sonstige Bursitis an der Hüfte" },
  { "code": "M70.9", "bezeichnung": "Weichteilkrankheit durch Beanspruchung, nicht näher bezeichnet" },
  { "code": "M71.0", "bezeichnung": "Schleimbeutelabszess" },
  { "code": "M71.2", "bezeichnung": "Synovialzyste des Kniegelenkes (Bakerzyste)" },
  { "code": "M71.3", "bezeichnung": "Sonstige Bursazyste" },
  { "code": "M71.9", "bezeichnung": "Bursopathie, nicht näher bezeichnet" },
  { "code": "M72.0", "bezeichnung": "Palmare Fibromatose (Dupuytren)" },
  { "code": "M72.2", "bezeichnung": "Plantare Fibromatose" },
  { "code": "M75.0", "bezeichnung": "Adhäsive Schultergelenkskapselitis" },
  { "code": "M75.1", "bezeichnung": "Schulterrotatorenmanschettenruptur" },
  { "code": "M75.2", "bezeichnung": "Bizeps-Tendinitis" },
  { "code": "M75.3", "bezeichnung": "Schulter-Kalktendinitis" },
  { "code": "M75.4", "bezeichnung": "Schulter-Impingement-Syndrom" },
  { "code": "M75.5", "bezeichnung": "Schulter-Bursitis" },
  { "code": "M75.9", "bezeichnung": "Schulterläsion, nicht näher bezeichnet" },
  { "code": "M76.0", "bezeichnung": "Glutäale Tendinitis" },
  { "code": "M76.1", "bezeichnung": "Psoastendinitis" },
  { "code": "M76.2", "bezeichnung": "Iliopsoastendinitis" },
  { "code": "M76.3", "bezeichnung": "Tractus-iliotibialis-Syndrom" },
  { "code": "M76.4", "bezeichnung": "Patellaspitze" },
  { "code": "M76.5", "bezeichnung": "Patellarsehnentendinitis" },
  { "code": "M76.6", "bezeichnung": "Achillessehnentendinitis" },
  { "code": "M76.7", "bezeichnung": "Peronealsehnensyndrom" },
  { "code": "M77.0", "bezeichnung": "Epicondylitis medialis humeri" },
  { "code": "M77.1", "bezeichnung": "Epicondylitis lateralis humeri (Tennisarm)" },
  { "code": "M77.2", "bezeichnung": "Periarthritis des Handgelenkes" },
  { "code": "M77.3", "bezeichnung": "Fersensporn" },
  { "code": "M77.5", "bezeichnung": "Sonstige Enthesopathie am Fuß" },
  { "code": "M77.8", "bezeichnung": "Sonstige Enthesopathien, anderenorts nicht klassifiziert" },
  { "code": "M77.9", "bezeichnung": "Enthesopathie, nicht näher bezeichnet" },
  { "code": "M79.0", "bezeichnung": "Rheumatismus, nicht näher bezeichnet" },
  { "code": "M79.1", "bezeichnung": "Myalgie" },
  { "code": "M79.2", "bezeichnung": "Neuralgie und Neuritis, nicht näher bezeichnet" },
  { "code": "M79.3", "bezeichnung": "Pannikulitis, nicht näher bezeichnet" },
  { "code": "M79.4", "bezeichnung": "Hypertrophie des Fettpolsters" },
  { "code": "M79.6", "bezeichnung": "Schmerzen in der Extremität" },
  { "code": "M79.7", "bezeichnung": "Fibromyalgie" },
  { "code": "M80.0", "bezeichnung": "Osteoporose durch Menopause mit pathologischer Fraktur" },
  { "code": "M81.0", "bezeichnung": "Postmenopausale Osteoporose" },
  { "code": "M81.9", "bezeichnung": "Osteoporose, nicht näher bezeichnet" },
  { "code": "M85.0", "bezeichnung": "Fibröse Dysplasie (monoostotisch)" },
  { "code": "M85.8", "bezeichnung": "Sonstige näher bezeichnete Knochendichteveränderungen" },
  { "code": "M86.9", "bezeichnung": "Osteomyelitis, nicht näher bezeichnet" },
  { "code": "M87.0", "bezeichnung": "Idiopathische Knochennekrose" },
  { "code": "M89.0", "bezeichnung": "Algodystrophie (Sudeck-Syndrom, CRPS Typ I)" },
  { "code": "M93.1", "bezeichnung": "Morbus Kienbock" },
  { "code": "M96.0", "bezeichnung": "Pseudarthrose nach Arthrodese" },
  { "code": "M99.0", "bezeichnung": "Segmentale und somatische Dysfunktion (Osteopathie)" },
  { "code": "M99.1", "bezeichnung": "Subluxationskomplex (vertebral)" },
  { "code": "G35", "bezeichnung": "Multiple Sklerose" },
  { "code": "G43.0", "bezeichnung": "Migräne ohne Aura (einfache Migräne)" },
  { "code": "G43.1", "bezeichnung": "Migräne mit Aura (klassische Migräne)" },
  { "code": "G43.3", "bezeichnung": "Komplizierte Migräne" },
  { "code": "G43.9", "bezeichnung": "Migräne, nicht näher bezeichnet" },
  { "code": "G44.2", "bezeichnung": "Spannungskopfschmerz" },
  { "code": "G44.8", "bezeichnung": "Sonstige näher bezeichnete Kopfschmerzsyndrome" },
  { "code": "G47.0", "bezeichnung": "Ein- und Durchschlafstörungen (Insomnie)" },
  { "code": "G50.0", "bezeichnung": "Trigeminusneuralgie" },
  { "code": "G51.0", "bezeichnung": "Bell-Lähmung (Fazialisparese)" },
  { "code": "G54.2", "bezeichnung": "Zervikale Wurzelläsion" },
  { "code": "G54.3", "bezeichnung": "Thorakale Wurzelläsion" },
  { "code": "G54.4", "bezeichnung": "Lumbale und lumbale Wurzelläsion" },
  { "code": "G54.5", "bezeichnung": "Neuralgische Schulteramyotrophie (Parsonage-Turner-Syndrom)" },
  { "code": "G55.1", "bezeichnung": "Nervenwurzel- und Plexuskompression bei Bandscheibenkrankheiten" },
  { "code": "G56.0", "bezeichnung": "Karpaltunnelsyndrom" },
  { "code": "G56.1", "bezeichnung": "Sulcus-ulnaris-Syndrom" },
  { "code": "G56.2", "bezeichnung": "Läsion des Nervus medianus" },
  { "code": "G56.3", "bezeichnung": "Läsion des Nervus ulnaris" },
  { "code": "G57.0", "bezeichnung": "Läsion des Nervus ischiadicus" },
  { "code": "G57.1", "bezeichnung": "Meralgia paraesthetica" },
  { "code": "G57.2", "bezeichnung": "Läsion des Nervus femoralis" },
  { "code": "G57.3", "bezeichnung": "Läsion des Nervus peronaeus communis" },
  { "code": "G57.5", "bezeichnung": "Tarsaltunnelsyndrom" },
  { "code": "G57.6", "bezeichnung": "Läsion des Nervus plantaris" },
  { "code": "G60.0", "bezeichnung": "Hereditäre motorische und sensible Neuropathie" },
  { "code": "G62.9", "bezeichnung": "Polyneuropathie, nicht näher bezeichnet" },
  { "code": "G70.0", "bezeichnung": "Myasthenia gravis" },
  { "code": "G71.0", "bezeichnung": "Muskeldystrophie" },
  { "code": "G80.0", "bezeichnung": "Spastische tetraplegische Zerebralparese" },
  { "code": "G80.1", "bezeichnung": "Spastische diplegische Zerebralparese" },
  { "code": "G80.2", "bezeichnung": "Infantile hemiplegische Zerebralparese" },
  { "code": "G80.9", "bezeichnung": "Infantile Zerebralparese, nicht näher bezeichnet" },
  { "code": "G81.0", "bezeichnung": "Schlaffe Hemiplegie" },
  { "code": "G81.1", "bezeichnung": "Spastische Hemiplegie" },
  { "code": "G81.9", "bezeichnung": "Hemiplegie, nicht näher bezeichnet" },
  { "code": "G82.2", "bezeichnung": "Paraplegie, nicht näher bezeichnet" },
  { "code": "G82.5", "bezeichnung": "Tetraplegie, nicht näher bezeichnet" },
  { "code": "G90.5", "bezeichnung": "Komplexes regionales Schmerzsyndrom Typ II (CRPS Typ II)" },
  { "code": "G91.0", "bezeichnung": "Kommunizierender Hydrozephalus" },
  { "code": "R25.0", "bezeichnung": "Abnorme Kopfbewegungen" },
  { "code": "R25.1", "bezeichnung": "Tremor, nicht näher bezeichnet" },
  { "code": "R25.2", "bezeichnung": "Krampf und Spasmen" },
  { "code": "R26.0", "bezeichnung": "Ataktischer Gang" },
  { "code": "R26.1", "bezeichnung": "Spastischer Gang" },
  { "code": "R26.2", "bezeichnung": "Erschwertes Gehen, anderenorts nicht klassifiziert" },
  { "code": "R26.9", "bezeichnung": "Gang- und Bewegungsstörungen, nicht näher bezeichnet" },
  { "code": "R29.0", "bezeichnung": "Tetanie" },
  { "code": "R29.3", "bezeichnung": "Abnorme Haltungsreflexe" },
  { "code": "R51", "bezeichnung": "Kopfschmerz" },
  { "code": "R52.0", "bezeichnung": "Akuter Schmerz" },
  { "code": "R52.1", "bezeichnung": "Chronischer unbeeinflussbarer Schmerz" },
  { "code": "R52.2", "bezeichnung": "Sonstiger chronischer Schmerz" },
  { "code": "R52.9", "bezeichnung": "Schmerz, nicht näher bezeichnet" },
  { "code": "R53", "bezeichnung": "Unwohlsein und Erschöpfung" },
  { "code": "R55", "bezeichnung": "Synkope und Kollaps" },
  { "code": "R68.8", "bezeichnung": "Sonstige näher bezeichnete allgemeine Symptome und Zeichen" },
  { "code": "S00.00", "bezeichnung": "Oberflächliche Verletzung des Kopfes" },
  { "code": "S09.9", "bezeichnung": "Verletzung des Kopfes, nicht näher bezeichnet (HWS-Distorsion)" },
  { "code": "S13.4", "bezeichnung": "Verstauchung und Zerrung der Halswirbelsäule" },
  { "code": "S14.1", "bezeichnung": "Sonstige und nicht näher bezeichnete Verletzungen der Halswirbelsäule" },
  { "code": "S20.0", "bezeichnung": "Prellung der Brustwarze" },
  { "code": "S23.3", "bezeichnung": "Verstauchung und Zerrung der Brustwirbelsäule" },
  { "code": "S30.0", "bezeichnung": "Prellung des unteren Rückens und des Beckens" },
  { "code": "S33.5", "bezeichnung": "Verstauchung und Zerrung der Lumbalwirbelsäule" },
  { "code": "S39.0", "bezeichnung": "Verletzung von Muskeln und Sehnen des unteren Rückens und des Beckens" },
  { "code": "S40.0", "bezeichnung": "Prellung der Schulter" },
  { "code": "S43.0", "bezeichnung": "Luxation des Schultergelenkes" },
  { "code": "S43.1", "bezeichnung": "Luxation des Acromioclaviculargelenkes" },
  { "code": "S43.4", "bezeichnung": "Verstauchung und Zerrung des Schultergelenkes" },
  { "code": "S46.0", "bezeichnung": "Verletzung der Rotatorenmanschette" },
  { "code": "S50.0", "bezeichnung": "Prellung des Ellenbogens" },
  { "code": "S52.5", "bezeichnung": "Fraktur des distalen Radius" },
  { "code": "S60.0", "bezeichnung": "Prellung des Daumens" },
  { "code": "S63.1", "bezeichnung": "Subluxation und Luxation des Handgelenkes" },
  { "code": "S70.0", "bezeichnung": "Prellung der Hüfte" },
  { "code": "S72.0", "bezeichnung": "Schenkelhalsfraktur" },
  { "code": "S72.1", "bezeichnung": "Pertrochanteräre Fraktur" },
  { "code": "S80.0", "bezeichnung": "Prellung der Kniescheibe" },
  { "code": "S83.0", "bezeichnung": "Luxation der Kniescheibe" },
  { "code": "S83.2", "bezeichnung": "Riss des Meniskus" },
  { "code": "S83.5", "bezeichnung": "Verstauchung und Zerrung des Kniegelenkes" },
  { "code": "S86.0", "bezeichnung": "Verletzung der Achillessehne" },
  { "code": "S86.1", "bezeichnung": "Verletzung sonstiger Muskeln und Sehnen der dorsalen Muskelgruppe" },
  { "code": "S90.0", "bezeichnung": "Prellung des oberen Sprunggelenkes und des Fußes" },
  { "code": "S93.0", "bezeichnung": "Luxation des Sprunggelenkes" },
  { "code": "S93.4", "bezeichnung": "Verstauchung und Zerrung des Sprunggelenkes" },
  { "code": "T08", "bezeichnung": "Fraktur der Wirbelsäule, Höhe nicht näher bezeichnet" },
  { "code": "T14.3", "bezeichnung": "Luxation, Verstauchung und Zerrung nicht näher bezeichneter Körperregion" },
  { "code": "F45.0", "bezeichnung": "Somatisierungsstörung" },
  { "code": "F45.1", "bezeichnung": "Undifferenzierte Somatisierungsstörung" },
  { "code": "F45.2", "bezeichnung": "Hypochondrische Störung" },
  { "code": "F45.4", "bezeichnung": "Anhaltende somatoforme Schmerzstörung" },
  { "code": "F48.0", "bezeichnung": "Neurasthenie (Erschöpfungssyndrom)" },
  { "code": "F50.0", "bezeichnung": "Anorexia nervosa" },
  { "code": "F54", "bezeichnung": "Psychologische Faktoren oder Verhaltensfaktoren bei anderenorts klassifizierten Krankheiten" },
  { "code": "F60.8", "bezeichnung": "Sonstige spezifische Persönlichkeitsstörungen" },
  { "code": "F43.2", "bezeichnung": "Anpassungsstörungen" },
  { "code": "F32.9", "bezeichnung": "Depressive Episode, nicht näher bezeichnet" },
  { "code": "I10", "bezeichnung": "Essentielle (primäre) Hypertonie" },
  { "code": "I50.9", "bezeichnung": "Herzinsuffizienz, nicht näher bezeichnet" },
  { "code": "I67.2", "bezeichnung": "Zerebrovaskuläre Atherosklerose" },
  { "code": "I63.9", "bezeichnung": "Hirninfarkt, nicht näher bezeichnet" },
  { "code": "I69.3", "bezeichnung": "Folgen eines Hirninfarkts" },
  { "code": "I69.4", "bezeichnung": "Folgen eines Schlaganfalls" },
  { "code": "E11.9", "bezeichnung": "Diabetes mellitus Typ 2, ohne Komplikationen" },
  { "code": "E66.0", "bezeichnung": "Adipositas durch übermäßige Kalorienzufuhr" },
  { "code": "E66.9", "bezeichnung": "Adipositas, nicht näher bezeichnet" },
  { "code": "E78.0", "bezeichnung": "Reine Hypercholesterinämie" },
  { "code": "J06.9", "bezeichnung": "Akute Infektion der oberen Atemwege, nicht näher bezeichnet" },
  { "code": "J44.1", "bezeichnung": "Chronisch obstruktive Lungenkrankheit mit akuter Exazerbation" },
  { "code": "K57.3", "bezeichnung": "Divertikulose des Dickdarms ohne Perforation oder Abszess" },
  { "code": "N39.0", "bezeichnung": "Harnwegsinfektion, Lokalisation nicht näher bezeichnet" },
  { "code": "Z73.0", "bezeichnung": "Erschöpfung (Burnout)" },
  { "code": "Z96.6", "bezeichnung": "Vorhandensein von orthopädischen Gelenkimplantaten" },
  { "code": "Z96.7", "bezeichnung": "Vorhandensein sonstiger Knochenchirurgie und Knochenimplantate" },
  { "code": "Z87.3", "bezeichnung": "Anamnestisch: Erkrankungen des muskuloskelettalen Systems" },
  { "code": "Z87.7", "bezeichnung": "Anamnestisch: Verletzungen und Vergiftungen" },
  { "code": "Z96.0", "bezeichnung": "Vorhandensein von Urogenitalimplantaten" }
]
